lsymm/__init__.py
lsymm/module.py
lsymm-0.0.3.dist-info/METADATA
lsymm-0.0.3.dist-info/WHEEL
lsymm-0.0.3.dist-info/top_level.txt
lsymm-0.0.3.dist-info/RECORD
